onec_dtools/__init__.py
onec_dtools/container_reader.py
onec_dtools/container_writer.py
onec_dtools/database_reader.py
onec_dtools/supply_reader.py
onec_dtools-0.5.0.dist-info/DESCRIPTION.rst
onec_dtools-0.5.0.dist-info/METADATA
onec_dtools-0.5.0.dist-info/RECORD
onec_dtools-0.5.0.dist-info/WHEEL
onec_dtools-0.5.0.dist-info/metadata.json
onec_dtools-0.5.0.dist-info/top_level.txt
