Metadata-Version: 2.0
Name: onec-dtools
Version: 0.5.0
Summary: Tools for working with 1C:Enterprise binary files
Home-page: https://github.com/Infactum/onec_dtools
Author: infactum
Author-email: infactum@gmail.com
License: MIT
